test/__init__.py
test/config_test.py
xx_framework/__init__.py
xx_framework/conf/__init__.py
xx_framework/conf/default_config.py
xx_framework/logs/__init__.py
xx_framework/redis/__init__.py
xx_framework/redis/wrappers.py
xx_framework/utils/__init__.py
xx_framework/utils/image_process.py
xx_framework-1.0.1.8.dist-info/METADATA
xx_framework-1.0.1.8.dist-info/WHEEL
xx_framework-1.0.1.8.dist-info/top_level.txt
xx_framework-1.0.1.8.dist-info/RECORD
